joern_lib/__init__.py
joern_lib/client.py
joern_lib/detectors/__init__.py
joern_lib/detectors/c.py
joern_lib/detectors/common.py
joern_lib/detectors/java.py
joern_lib/detectors/js.py
joern_lib/detectors/python.py
joern_lib/graph.py
joern_lib/utils.py
joern_lib/workspace.py
joern_lib-0.12.0.dist-info/LICENSE
joern_lib-0.12.0.dist-info/METADATA
joern_lib-0.12.0.dist-info/WHEEL
joern_lib-0.12.0.dist-info/RECORD
