Metadata-Version: 2.1
Name: joern-lib
Version: 0.12.0
Summary: Python library for code analysis with CPG and Joern
Home-page: https://github.com/AppThreat/joern-lib
License: Apache-2.0
Keywords: joern,code analysis,static analysis
Author: Team AppThreat
Author-email: cloud@appthreat.com
Requires-Python: >=3.8.1,<3.12
Classifier: Development Status :: 5 - Production/Stable
Classifier: Intended Audience :: Developers
Classifier: Intended Audience :: System Administrators
Classifier: License :: OSI Approved :: Apache Software License
Classifier: Operating System :: OS Independent
Classifier: Programming Language :: Python :: 3
Classifier: Programming Language :: Python :: 3.9
Classifier: Programming Language :: Python :: 3.10
Classifier: Programming Language :: Python :: 3.11
Classifier: Programming Language :: Python :: 3.8
Classifier: Topic :: Security
Classifier: Topic :: Utilities
Requires-Dist: httpx (>=0.24.1,<0.25.0)
Requires-Dist: networkx[default] (>=3.1,<4.0)
Requires-Dist: orjson (>=3.9.0,<4.0.0)
Requires-Dist: pydotplus (>=2.0.2,<3.0.0)
Requires-Dist: pygraphviz (>=1.10,<2.0)
Requires-Dist: rich (>=13.4.1,<14.0.0)
Requires-Dist: uvloop (>=0.17.0,<0.18.0)
Requires-Dist: websockets (>=11.0.2,<12.0.0)
Project-URL: Repository, https://github.com/AppThreat/joern-lib
